batchata/__init__.py
batchata/exceptions.py
batchata/types.py
batchata/core/__init__.py
batchata/core/batch.py
batchata/core/batch_params.py
batchata/core/batch_run.py
batchata/core/job.py
batchata/core/job_result.py
batchata/providers/__init__.py
batchata/providers/model_config.py
batchata/providers/provider.py
batchata/providers/provider_registry.py
batchata/providers/anthropic/__init__.py
batchata/providers/anthropic/anthropic.py
batchata/providers/anthropic/citation_mapper.py
batchata/providers/anthropic/message_prepare.py
batchata/providers/anthropic/models.py
batchata/providers/anthropic/parse_results.py
batchata/providers/gemini/__init__.py
batchata/providers/gemini/gemini_provider.py
batchata/providers/gemini/message_prepare.py
batchata/providers/gemini/models.py
batchata/providers/gemini/parse_results.py
batchata/providers/openai/__init__.py
batchata/providers/openai/message_prepare.py
batchata/providers/openai/models.py
batchata/providers/openai/openai_provider.py
batchata/providers/openai/parse_results.py
batchata/utils/__init__.py
batchata/utils/cost.py
batchata/utils/llm.py
batchata/utils/logging.py
batchata/utils/pdf.py
batchata/utils/rich_progress.py
batchata/utils/serialization.py
batchata/utils/state.py
batchata/utils/validation.py
batchata-0.4.7.dist-info/METADATA
batchata-0.4.7.dist-info/WHEEL
batchata-0.4.7.dist-info/entry_points.txt
batchata-0.4.7.dist-info/RECORD
