Metadata-Version: 2.4
Name: batchata
Version: 0.4.7
Summary: Unified Python API for AI batch requests with 50% cost savings on OpenAI and Anthropic
Project-URL: Homepage, https://github.com/agamm/batchata
Project-URL: Repository, https://github.com/agamm/batchata
Project-URL: Documentation, https://agamm.github.io/batchata/
Project-URL: Issues, https://github.com/agamm/batchata/issues
Project-URL: Changelog, https://github.com/agamm/batchata/releases
Author: Agam More
License: MIT
Keywords: ai,ai-batch,ai-tools,anthropic,anthropic-batch,api,async,batch,batch-api,batch-processing,batch-requests,claude,cost-optimization,gemini,gemini-batch,google,gpt,llm,llm-batch,llms,machine-learning,openai,openai-batch
Classifier: Development Status :: 4 - Beta
Classifier: Intended Audience :: Developers
Classifier: License :: OSI Approved :: MIT License
Classifier: Natural Language :: English
Classifier: Operating System :: OS Independent
Classifier: Programming Language :: Python :: 3
Classifier: Programming Language :: Python :: 3.12
Classifier: Programming Language :: Python :: 3.13
Classifier: Topic :: Internet :: WWW/HTTP :: Dynamic Content
Classifier: Topic :: Scientific/Engineering :: Artificial Intelligence
Classifier: Topic :: Software Development :: Libraries :: Python Modules
Classifier: Typing :: Typed
Requires-Python: >=3.12
Requires-Dist: anthropic>=0.57.1
Requires-Dist: google-genai>=0.8.0
Requires-Dist: openai>=1.97.0
Requires-Dist: pydantic>=2.0
Requires-Dist: pypdf>=5.8.0
Requires-Dist: pytest-asyncio>=1.1.0
Requires-Dist: rich>=14.0.0
Requires-Dist: tokencost>=0.1.24
